af_execution_manager/__init__.py
af_execution_manager/api_client.py
af_execution_manager/configuration.py
af_execution_manager/rest.py
af_execution_manager/api/__init__.py
af_execution_manager/api/activity_execution_control_api.py
af_execution_manager/api/activity_starting_api.py
af_execution_manager/api/activity_termination_api.py
af_execution_manager/api/arch_inst_id_remote_iterator_api.py
af_execution_manager/api/arch_templ_id_remote_iterator_api.py
af_execution_manager/api/arista_flow_service_api.py
af_execution_manager/api/configurable_arista_flow_service_api.py
af_execution_manager/api/default_api.py
af_execution_manager/api/ec_remote_iterator_api.py
af_execution_manager/api/execution_manager_api.py
af_execution_manager/api/instance_control_api.py
af_execution_manager/api/qa_remote_iterator_api.py
af_execution_manager/api/templ_id_remote_iterator_api.py
af_execution_manager/api/templ_ref_remote_iterator_rest_api.py
af_execution_manager/models/__init__.py
af_execution_manager/models/abort_service_exception.py
af_execution_manager/models/abort_transaction_exception.py
af_execution_manager/models/accessed_process_model_parameter.py
af_execution_manager/models/activity_configuration.py
af_execution_manager/models/activity_data_container.py
af_execution_manager/models/activity_instance.py
af_execution_manager/models/activity_ref_with_dc_data.py
af_execution_manager/models/activity_ref_with_dc_sp_data.py
af_execution_manager/models/activity_ref_with_failure_data.py
af_execution_manager/models/activity_ref_with_sp_data.py
af_execution_manager/models/activity_reference_data.py
af_execution_manager/models/af_configuration.py
af_execution_manager/models/agent_unknown_exception.py
af_execution_manager/models/archive_template_response.py
af_execution_manager/models/authentication_exception.py
af_execution_manager/models/auto_start_pending_data.py
af_execution_manager/models/body.py
af_execution_manager/models/body1.py
af_execution_manager-4.0.3.dist-info/LICENSE
af_execution_manager-4.0.3.dist-info/METADATA
af_execution_manager-4.0.3.dist-info/WHEEL
af_execution_manager-4.0.3.dist-info/top_level.txt
af_execution_manager-4.0.3.dist-info/RECORD
